azure/mgmt/sphere/__init__.py
azure/mgmt/sphere/_azure_sphere_mgmt_client.py
azure/mgmt/sphere/_configuration.py
azure/mgmt/sphere/_patch.py
azure/mgmt/sphere/_serialization.py
azure/mgmt/sphere/_vendor.py
azure/mgmt/sphere/_version.py
azure/mgmt/sphere/py.typed
azure/mgmt/sphere/aio/__init__.py
azure/mgmt/sphere/aio/_azure_sphere_mgmt_client.py
azure/mgmt/sphere/aio/_configuration.py
azure/mgmt/sphere/aio/_patch.py
azure/mgmt/sphere/aio/operations/__init__.py
azure/mgmt/sphere/aio/operations/_catalogs_operations.py
azure/mgmt/sphere/aio/operations/_certificates_operations.py
azure/mgmt/sphere/aio/operations/_deployments_operations.py
azure/mgmt/sphere/aio/operations/_device_groups_operations.py
azure/mgmt/sphere/aio/operations/_devices_operations.py
azure/mgmt/sphere/aio/operations/_images_operations.py
azure/mgmt/sphere/aio/operations/_operations.py
azure/mgmt/sphere/aio/operations/_patch.py
azure/mgmt/sphere/aio/operations/_products_operations.py
azure/mgmt/sphere/models/__init__.py
azure/mgmt/sphere/models/_azure_sphere_mgmt_client_enums.py
azure/mgmt/sphere/models/_models_py3.py
azure/mgmt/sphere/models/_patch.py
azure/mgmt/sphere/operations/__init__.py
azure/mgmt/sphere/operations/_catalogs_operations.py
azure/mgmt/sphere/operations/_certificates_operations.py
azure/mgmt/sphere/operations/_deployments_operations.py
azure/mgmt/sphere/operations/_device_groups_operations.py
azure/mgmt/sphere/operations/_devices_operations.py
azure/mgmt/sphere/operations/_images_operations.py
azure/mgmt/sphere/operations/_operations.py
azure/mgmt/sphere/operations/_patch.py
azure/mgmt/sphere/operations/_products_operations.py
azure_mgmt_sphere-1.0.0.dist-info/LICENSE
azure_mgmt_sphere-1.0.0.dist-info/METADATA
azure_mgmt_sphere-1.0.0.dist-info/WHEEL
azure_mgmt_sphere-1.0.0.dist-info/top_level.txt
azure_mgmt_sphere-1.0.0.dist-info/RECORD
